{"orders": [{"order_id": 10056, "pickup_point_id": 40056, "pickup_from": 390, "pickup_to": 450, "pickup_location_x": 49, "pickup_location_y": 59, "dropoff_point_id": 60056, "dropoff_from": 540, "dropoff_to": 600, "dropoff_location_x": 259, "dropoff_location_y": 74, "payment": 545}, {"order_id": 11488, "pickup_point_id": 41488, "pickup_from": 425, "pickup_to": 480, "pickup_location_x": 113, "pickup_location_y": 63, "dropoff_point_id": 61488, "dropoff_from": 425, "dropoff_to": 510, "dropoff_location_x": 204, "dropoff_location_y": 120, "payment": 316}, {"order_id": 12884, "pickup_point_id": 42884, "pickup_from": 526, "pickup_to": 570, "pickup_location_x": 66, "pickup_location_y": 61, "dropoff_point_id": 62884, "dropoff_from": 526, "dropoff_to": 660, "dropoff_location_x": 247, "dropoff_location_y": 139, "payment": 500}, {"order_id": 13168, "pickup_point_id": 43168, "pickup_from": 544, "pickup_to": 600, "pickup_location_x": 175, "pickup_location_y": 59, "dropoff_point_id": 63168, "dropoff_from": 544, "dropoff_to": 690, "dropoff_location_x": 137, "dropoff_location_y": 135, "payment": 324}, {"order_id": 13467, "pickup_point_id": 43467, "pickup_from": 564, "pickup_to": 600, "pickup_location_x": 158, "pickup_location_y": 64, "dropoff_point_id": 63467, "dropoff_from": 564, "dropoff_to": 630, "dropoff_location_x": 157, "dropoff_location_y": 61, "payment": 175}, {"order_id": 14427, "pickup_point_id": 44427, "pickup_from": 660, "pickup_to": 720, "pickup_location_x": 202, "pickup_location_y": 58, "dropoff_point_id": 64427, "dropoff_from": 660, "dropoff_to": 810, "dropoff_location_x": 100, "dropoff_location_y": 82, "payment": 422}, {"order_id": 15343, "pickup_point_id": 45343, "pickup_from": 390, "pickup_to": 780, "pickup_location_x": 113, "pickup_location_y": 63, "dropoff_point_id": 65343, "dropoff_from": 700, "dropoff_to": 810, "dropoff_location_x": 200, "dropoff_location_y": 73, "payment": 366}, {"order_id": 15890, "pickup_point_id": 45890, "pickup_from": 360, "pickup_to": 810, "pickup_location_x": 218, "pickup_location_y": 61, "dropoff_point_id": 65890, "dropoff_from": 1020, "dropoff_to": 1050, "dropoff_location_x": 91, "dropoff_location_y": 131, "payment": 397}, {"order_id": 16539, "pickup_point_id": 46539, "pickup_from": 420, "pickup_to": 960, "pickup_location_x": 202, "pickup_location_y": 62, "dropoff_point_id": 66539, "dropoff_from": 900, "dropoff_to": 1080, "dropoff_location_x": 111, "dropoff_location_y": 74, "payment": 482}, {"order_id": 16916, "pickup_point_id": 46916, "pickup_from": 420, "pickup_to": 960, "pickup_location_x": 202, "pickup_location_y": 62, "dropoff_point_id": 66916, "dropoff_from": 886, "dropoff_to": 1080, "dropoff_location_x": 111, "dropoff_location_y": 74, "payment": 482}, {"order_id": 16976, "pickup_point_id": 46976, "pickup_from": 420, "pickup_to": 1050, "pickup_location_x": 122, "pickup_location_y": 66, "dropoff_point_id": 66976, "dropoff_from": 1050, "dropoff_to": 1110, "dropoff_location_x": 196, "dropoff_location_y": 4, "payment": 339}], "depots": [], "couriers": []}