{"orders": [{"order_id": 10266, "pickup_point_id": 40266, "pickup_from": 360, "pickup_to": 840, "pickup_location_x": 123, "pickup_location_y": 139, "dropoff_point_id": 60266, "dropoff_from": 720, "dropoff_to": 960, "dropoff_location_x": 355, "dropoff_location_y": 154, "payment": 457}, {"order_id": 11296, "pickup_point_id": 41296, "pickup_from": 390, "pickup_to": 870, "pickup_location_x": 122, "pickup_location_y": 90, "dropoff_point_id": 61296, "dropoff_from": 900, "dropoff_to": 1020, "dropoff_location_x": 223, "dropoff_location_y": 171, "payment": 457}, {"order_id": 11833, "pickup_point_id": 41833, "pickup_from": 390, "pickup_to": 900, "pickup_location_x": 307, "pickup_location_y": 59, "dropoff_point_id": 61833, "dropoff_from": 960, "dropoff_to": 1020, "dropoff_location_x": 324, "dropoff_location_y": 161, "payment": 428}, {"order_id": 12126, "pickup_point_id": 42126, "pickup_from": 474, "pickup_to": 900, "pickup_location_x": 242, "pickup_location_y": 103, "dropoff_point_id": 62126, "dropoff_from": 474, "dropoff_to": 1020, "dropoff_location_x": 341, "dropoff_location_y": 96, "payment": 274}, {"order_id": 12265, "pickup_point_id": 42265, "pickup_from": 484, "pickup_to": 900, "pickup_location_x": 183, "pickup_location_y": 23, "dropoff_point_id": 62265, "dropoff_from": 484, "dropoff_to": 930, "dropoff_location_x": 304, "dropoff_location_y": 143, "payment": 354}, {"order_id": 12347, "pickup_point_id": 42347, "pickup_from": 390, "pickup_to": 870, "pickup_location_x": 82, "pickup_location_y": 22, "dropoff_point_id": 62347, "dropoff_from": 870, "dropoff_to": 960, "dropoff_location_x": 183, "dropoff_location_y": 102, "payment": 290}, {"order_id": 12518, "pickup_point_id": 42518, "pickup_from": 360, "pickup_to": 840, "pickup_location_x": 166, "pickup_location_y": 10, "dropoff_point_id": 62518, "dropoff_from": 900, "dropoff_to": 1020, "dropoff_location_x": 253, "dropoff_location_y": 94, "payment": 380}, {"order_id": 13001, "pickup_point_id": 43001, "pickup_from": 534, "pickup_to": 840, "pickup_location_x": 22, "pickup_location_y": 114, "dropoff_point_id": 63001, "dropoff_from": 840, "dropoff_to": 1020, "dropoff_location_x": 167, "dropoff_location_y": 155, "payment": 376}, {"order_id": 13025, "pickup_point_id": 43025, "pickup_from": 536, "pickup_to": 930, "pickup_location_x": 138, "pickup_location_y": 80, "dropoff_point_id": 63025, "dropoff_from": 536, "dropoff_to": 930, "dropoff_location_x": 332, "dropoff_location_y": 166, "payment": 375}, {"order_id": 13160, "pickup_point_id": 43160, "pickup_from": 360, "pickup_to": 960, "pickup_location_x": 73, "pickup_location_y": 131, "dropoff_point_id": 63160, "dropoff_from": 750, "dropoff_to": 990, "dropoff_location_x": 249, "dropoff_location_y": 172, "payment": 329}, {"order_id": 13383, "pickup_point_id": 43383, "pickup_from": 558, "pickup_to": 930, "pickup_location_x": 236, "pickup_location_y": 118, "dropoff_point_id": 63383, "dropoff_from": 960, "dropoff_to": 1050, "dropoff_location_x": 355, "dropoff_location_y": 149, "payment": 455}, {"order_id": 13407, "pickup_point_id": 43407, "pickup_from": 559, "pickup_to": 840, "pickup_location_x": 140, "pickup_location_y": 50, "dropoff_point_id": 63407, "dropoff_from": 559, "dropoff_to": 990, "dropoff_location_x": 297, "dropoff_location_y": 117, "payment": 461}, {"order_id": 13466, "pickup_point_id": 43466, "pickup_from": 564, "pickup_to": 930, "pickup_location_x": 61, "pickup_location_y": 137, "dropoff_point_id": 63466, "dropoff_from": 564, "dropoff_to": 960, "dropoff_location_x": 180, "dropoff_location_y": 208, "payment": 500}, {"order_id": 13703, "pickup_point_id": 43703, "pickup_from": 579, "pickup_to": 900, "pickup_location_x": 152, "pickup_location_y": 87, "dropoff_point_id": 63703, "dropoff_from": 579, "dropoff_to": 960, "dropoff_location_x": 224, "dropoff_location_y": 145, "payment": 271}, {"order_id": 13898, "pickup_point_id": 43898, "pickup_from": 630, "pickup_to": 900, "pickup_location_x": 173, "pickup_location_y": 192, "dropoff_point_id": 63898, "dropoff_from": 720, "dropoff_to": 1080, "dropoff_location_x": 280, "dropoff_location_y": 247, "payment": 503}, {"order_id": 13899, "pickup_point_id": 43899, "pickup_from": 630, "pickup_to": 870, "pickup_location_x": 59, "pickup_location_y": 123, "dropoff_point_id": 63899, "dropoff_from": 630, "dropoff_to": 990, "dropoff_location_x": 103, "dropoff_location_y": 149, "payment": 250}, {"order_id": 14014, "pickup_point_id": 44014, "pickup_from": 390, "pickup_to": 930, "pickup_location_x": 205, "pickup_location_y": 4, "dropoff_point_id": 64014, "dropoff_from": 930, "dropoff_to": 1020, "dropoff_location_x": 288, "dropoff_location_y": 106, "payment": 467}, {"order_id": 14019, "pickup_point_id": 44019, "pickup_from": 602, "pickup_to": 900, "pickup_location_x": 120, "pickup_location_y": 25, "dropoff_point_id": 64019, "dropoff_from": 602, "dropoff_to": 1050, "dropoff_location_x": 213, "dropoff_location_y": 118, "payment": 350}, {"order_id": 14130, "pickup_point_id": 44130, "pickup_from": 660, "pickup_to": 900, "pickup_location_x": 81, "pickup_location_y": 20, "dropoff_point_id": 64130, "dropoff_from": 660, "dropoff_to": 1020, "dropoff_location_x": 230, "dropoff_location_y": 98, "payment": 463}, {"order_id": 14176, "pickup_point_id": 44176, "pickup_from": 420, "pickup_to": 870, "pickup_location_x": 168, "pickup_location_y": 9, "dropoff_point_id": 64176, "dropoff_from": 810, "dropoff_to": 960, "dropoff_location_x": 282, "dropoff_location_y": 118, "payment": 532}, {"order_id": 14260, "pickup_point_id": 44260, "pickup_from": 420, "pickup_to": 900, "pickup_location_x": 110, "pickup_location_y": 131, "dropoff_point_id": 64260, "dropoff_from": 960, "dropoff_to": 990, "dropoff_location_x": 162, "dropoff_location_y": 222, "payment": 400}, {"order_id": 14376, "pickup_point_id": 44376, "pickup_from": 660, "pickup_to": 900, "pickup_location_x": 178, "pickup_location_y": 6, "dropoff_point_id": 64376, "dropoff_from": 840, "dropoff_to": 1080, "dropoff_location_x": 355, "dropoff_location_y": 135, "payment": 460}, {"order_id": 14602, "pickup_point_id": 44602, "pickup_from": 360, "pickup_to": 870, "pickup_location_x": 141, "pickup_location_y": 19, "dropoff_point_id": 64602, "dropoff_from": 720, "dropoff_to": 976, "dropoff_location_x": 194, "dropoff_location_y": 111, "payment": 608}, {"order_id": 14697, "pickup_point_id": 44697, "pickup_from": 420, "pickup_to": 930, "pickup_location_x": 217, "pickup_location_y": 61, "dropoff_point_id": 64697, "dropoff_from": 720, "dropoff_to": 960, "dropoff_location_x": 301, "dropoff_location_y": 171, "payment": 418}, {"order_id": 14864, "pickup_point_id": 44864, "pickup_from": 420, "pickup_to": 960, "pickup_location_x": 81, "pickup_location_y": 20, "dropoff_point_id": 64864, "dropoff_from": 720, "dropoff_to": 960, "dropoff_location_x": 380, "dropoff_location_y": 99, "payment": 409}, {"order_id": 15153, "pickup_point_id": 45153, "pickup_from": 330, "pickup_to": 960, "pickup_location_x": 4, "pickup_location_y": 109, "dropoff_point_id": 65153, "dropoff_from": 720, "dropoff_to": 960, "dropoff_location_x": 90, "dropoff_location_y": 225, "payment": 402}, {"order_id": 15264, "pickup_point_id": 45264, "pickup_from": 390, "pickup_to": 840, "pickup_location_x": 144, "pickup_location_y": 18, "dropoff_point_id": 65264, "dropoff_from": 840, "dropoff_to": 1050, "dropoff_location_x": 320, "dropoff_location_y": 122, "payment": 542}, {"order_id": 15319, "pickup_point_id": 45319, "pickup_from": 330, "pickup_to": 840, "pickup_location_x": 166, "pickup_location_y": 7, "dropoff_point_id": 65319, "dropoff_from": 870, "dropoff_to": 1020, "dropoff_location_x": 224, "dropoff_location_y": 142, "payment": 413}, {"order_id": 15446, "pickup_point_id": 45446, "pickup_from": 360, "pickup_to": 840, "pickup_location_x": 186, "pickup_location_y": 18, "dropoff_point_id": 65446, "dropoff_from": 900, "dropoff_to": 990, "dropoff_location_x": 194, "dropoff_location_y": 279, "payment": 584}, {"order_id": 15613, "pickup_point_id": 45613, "pickup_from": 390, "pickup_to": 900, "pickup_location_x": 161, "pickup_location_y": 2, "dropoff_point_id": 65613, "dropoff_from": 840, "dropoff_to": 990, "dropoff_location_x": 320, "dropoff_location_y": 122, "payment": 501}, {"order_id": 15635, "pickup_point_id": 45635, "pickup_from": 330, "pickup_to": 840, "pickup_location_x": 82, "pickup_location_y": 22, "dropoff_point_id": 65635, "dropoff_from": 724, "dropoff_to": 960, "dropoff_location_x": 218, "dropoff_location_y": 168, "payment": 538}, {"order_id": 15808, "pickup_point_id": 45808, "pickup_from": 390, "pickup_to": 900, "pickup_location_x": 185, "pickup_location_y": 7, "dropoff_point_id": 65808, "dropoff_from": 740, "dropoff_to": 1020, "dropoff_location_x": 219, "dropoff_location_y": 171, "payment": 459}, {"order_id": 15872, "pickup_point_id": 45872, "pickup_from": 360, "pickup_to": 960, "pickup_location_x": 162, "pickup_location_y": 149, "dropoff_point_id": 65872, "dropoff_from": 747, "dropoff_to": 990, "dropoff_location_x": 350, "dropoff_location_y": 175, "payment": 785}, {"order_id": 15891, "pickup_point_id": 45891, "pickup_from": 330, "pickup_to": 900, "pickup_location_x": 235, "pickup_location_y": 132, "dropoff_point_id": 65891, "dropoff_from": 1020, "dropoff_to": 1050, "dropoff_location_x": 365, "dropoff_location_y": 161, "payment": 327}, {"order_id": 15911, "pickup_point_id": 45911, "pickup_from": 330, "pickup_to": 900, "pickup_location_x": 211, "pickup_location_y": 80, "dropoff_point_id": 65911, "dropoff_from": 900, "dropoff_to": 1020, "dropoff_location_x": 277, "dropoff_location_y": 257, "payment": 393}, {"order_id": 15922, "pickup_point_id": 45922, "pickup_from": 300, "pickup_to": 900, "pickup_location_x": 191, "pickup_location_y": 8, "dropoff_point_id": 65922, "dropoff_from": 900, "dropoff_to": 1020, "dropoff_location_x": 275, "dropoff_location_y": 193, "payment": 462}, {"order_id": 15938, "pickup_point_id": 45938, "pickup_from": 330, "pickup_to": 900, "pickup_location_x": 290, "pickup_location_y": 15, "dropoff_point_id": 65938, "dropoff_from": 900, "dropoff_to": 1050, "dropoff_location_x": 375, "dropoff_location_y": 123, "payment": 408}, {"order_id": 15943, "pickup_point_id": 45943, "pickup_from": 390, "pickup_to": 900, "pickup_location_x": 175, "pickup_location_y": 3, "dropoff_point_id": 65943, "dropoff_from": 900, "dropoff_to": 1050, "dropoff_location_x": 228, "dropoff_location_y": 124, "payment": 424}, {"order_id": 15949, "pickup_point_id": 45949, "pickup_from": 330, "pickup_to": 840, "pickup_location_x": 178, "pickup_location_y": 3, "dropoff_point_id": 65949, "dropoff_from": 840, "dropoff_to": 1020, "dropoff_location_x": 243, "dropoff_location_y": 39, "payment": 522}, {"order_id": 16029, "pickup_point_id": 46029, "pickup_from": 390, "pickup_to": 840, "pickup_location_x": 198, "pickup_location_y": 63, "dropoff_point_id": 66029, "dropoff_from": 840, "dropoff_to": 990, "dropoff_location_x": 284, "dropoff_location_y": 218, "payment": 531}, {"order_id": 16042, "pickup_point_id": 46042, "pickup_from": 300, "pickup_to": 900, "pickup_location_x": 148, "pickup_location_y": 95, "dropoff_point_id": 66042, "dropoff_from": 763, "dropoff_to": 930, "dropoff_location_x": 212, "dropoff_location_y": 255, "payment": 314}, {"order_id": 16043, "pickup_point_id": 46043, "pickup_from": 420, "pickup_to": 870, "pickup_location_x": 198, "pickup_location_y": 201, "dropoff_point_id": 66043, "dropoff_from": 930, "dropoff_to": 990, "dropoff_location_x": 270, "dropoff_location_y": 198, "payment": 380}, {"order_id": 16053, "pickup_point_id": 46053, "pickup_from": 300, "pickup_to": 870, "pickup_location_x": 228, "pickup_location_y": 121, "dropoff_point_id": 66053, "dropoff_from": 930, "dropoff_to": 960, "dropoff_location_x": 289, "dropoff_location_y": 234, "payment": 393}, {"order_id": 16064, "pickup_point_id": 46064, "pickup_from": 300, "pickup_to": 960, "pickup_location_x": 165, "pickup_location_y": 9, "dropoff_point_id": 66064, "dropoff_from": 766, "dropoff_to": 1020, "dropoff_location_x": 356, "dropoff_location_y": 163, "payment": 629}, {"order_id": 16073, "pickup_point_id": 46073, "pickup_from": 330, "pickup_to": 840, "pickup_location_x": 151, "pickup_location_y": 14, "dropoff_point_id": 66073, "dropoff_from": 766, "dropoff_to": 1020, "dropoff_location_x": 161, "dropoff_location_y": 199, "payment": 483}, {"order_id": 16107, "pickup_point_id": 46107, "pickup_from": 360, "pickup_to": 840, "pickup_location_x": 12, "pickup_location_y": 103, "dropoff_point_id": 66107, "dropoff_from": 990, "dropoff_to": 1020, "dropoff_location_x": 243, "dropoff_location_y": 171, "payment": 372}, {"order_id": 16138, "pickup_point_id": 46138, "pickup_from": 420, "pickup_to": 870, "pickup_location_x": 115, "pickup_location_y": 46, "dropoff_point_id": 66138, "dropoff_from": 900, "dropoff_to": 960, "dropoff_location_x": 157, "dropoff_location_y": 271, "payment": 527}, {"order_id": 16139, "pickup_point_id": 46139, "pickup_from": 300, "pickup_to": 870, "pickup_location_x": 209, "pickup_location_y": 82, "dropoff_point_id": 66139, "dropoff_from": 840, "dropoff_to": 1027, "dropoff_location_x": 350, "dropoff_location_y": 114, "payment": 395}, {"order_id": 16207, "pickup_point_id": 46207, "pickup_from": 420, "pickup_to": 840, "pickup_location_x": 193, "pickup_location_y": 6, "dropoff_point_id": 66207, "dropoff_from": 960, "dropoff_to": 990, "dropoff_location_x": 217, "dropoff_location_y": 95, "payment": 350}, {"order_id": 16240, "pickup_point_id": 46240, "pickup_from": 300, "pickup_to": 870, "pickup_location_x": 135, "pickup_location_y": 139, "dropoff_point_id": 66240, "dropoff_from": 840, "dropoff_to": 1015, "dropoff_location_x": 176, "dropoff_location_y": 188, "payment": 343}, {"order_id": 16251, "pickup_point_id": 46251, "pickup_from": 360, "pickup_to": 870, "pickup_location_x": 165, "pickup_location_y": 105, "dropoff_point_id": 66251, "dropoff_from": 840, "dropoff_to": 1020, "dropoff_location_x": 360, "dropoff_location_y": 146, "payment": 407}, {"order_id": 16252, "pickup_point_id": 46252, "pickup_from": 330, "pickup_to": 900, "pickup_location_x": 82, "pickup_location_y": 22, "dropoff_point_id": 66252, "dropoff_from": 840, "dropoff_to": 1020, "dropoff_location_x": 361, "dropoff_location_y": 122, "payment": 700}, {"order_id": 16283, "pickup_point_id": 46283, "pickup_from": 360, "pickup_to": 930, "pickup_location_x": 102, "pickup_location_y": 117, "dropoff_point_id": 66283, "dropoff_from": 788, "dropoff_to": 960, "dropoff_location_x": 225, "dropoff_location_y": 245, "payment": 406}, {"order_id": 16286, "pickup_point_id": 46286, "pickup_from": 420, "pickup_to": 900, "pickup_location_x": 104, "pickup_location_y": 2, "dropoff_point_id": 66286, "dropoff_from": 788, "dropoff_to": 930, "dropoff_location_x": 233, "dropoff_location_y": 136, "payment": 428}, {"order_id": 16307, "pickup_point_id": 46307, "pickup_from": 330, "pickup_to": 870, "pickup_location_x": 120, "pickup_location_y": 153, "dropoff_point_id": 66307, "dropoff_from": 840, "dropoff_to": 960, "dropoff_location_x": 219, "dropoff_location_y": 191, "payment": 359}, {"order_id": 16360, "pickup_point_id": 46360, "pickup_from": 390, "pickup_to": 930, "pickup_location_x": 168, "pickup_location_y": 22, "dropoff_point_id": 66360, "dropoff_from": 796, "dropoff_to": 1020, "dropoff_location_x": 258, "dropoff_location_y": 121, "payment": 503}, {"order_id": 16362, "pickup_point_id": 46362, "pickup_from": 330, "pickup_to": 840, "pickup_location_x": 104, "pickup_location_y": 91, "dropoff_point_id": 66362, "dropoff_from": 797, "dropoff_to": 1020, "dropoff_location_x": 262, "dropoff_location_y": 187, "payment": 874}, {"order_id": 16366, "pickup_point_id": 46366, "pickup_from": 420, "pickup_to": 870, "pickup_location_x": 113, "pickup_location_y": 1, "dropoff_point_id": 66366, "dropoff_from": 930, "dropoff_to": 990, "dropoff_location_x": 237, "dropoff_location_y": 128, "payment": 555}, {"order_id": 16372, "pickup_point_id": 46372, "pickup_from": 300, "pickup_to": 870, "pickup_location_x": 123, "pickup_location_y": 17, "dropoff_point_id": 66372, "dropoff_from": 798, "dropoff_to": 960, "dropoff_location_x": 162, "dropoff_location_y": 185, "payment": 688}, {"order_id": 16418, "pickup_point_id": 46418, "pickup_from": 390, "pickup_to": 840, "pickup_location_x": 51, "pickup_location_y": 75, "dropoff_point_id": 66418, "dropoff_from": 803, "dropoff_to": 960, "dropoff_location_x": 366, "dropoff_location_y": 118, "payment": 510}, {"order_id": 16425, "pickup_point_id": 46425, "pickup_from": 330, "pickup_to": 870, "pickup_location_x": 41, "pickup_location_y": 65, "dropoff_point_id": 66425, "dropoff_from": 803, "dropoff_to": 960, "dropoff_location_x": 338, "dropoff_location_y": 168, "payment": 370}, {"order_id": 16427, "pickup_point_id": 46427, "pickup_from": 330, "pickup_to": 870, "pickup_location_x": 77, "pickup_location_y": 48, "dropoff_point_id": 66427, "dropoff_from": 803, "dropoff_to": 990, "dropoff_location_x": 321, "dropoff_location_y": 144, "payment": 390}, {"order_id": 16430, "pickup_point_id": 46430, "pickup_from": 330, "pickup_to": 870, "pickup_location_x": 273, "pickup_location_y": 11, "dropoff_point_id": 66430, "dropoff_from": 870, "dropoff_to": 1020, "dropoff_location_x": 244, "dropoff_location_y": 128, "payment": 390}, {"order_id": 16435, "pickup_point_id": 46435, "pickup_from": 300, "pickup_to": 900, "pickup_location_x": 209, "pickup_location_y": 82, "dropoff_point_id": 66435, "dropoff_from": 804, "dropoff_to": 960, "dropoff_location_x": 264, "dropoff_location_y": 215, "payment": 380}, {"order_id": 16457, "pickup_point_id": 46457, "pickup_from": 300, "pickup_to": 870, "pickup_location_x": 21, "pickup_location_y": 124, "dropoff_point_id": 66457, "dropoff_from": 806, "dropoff_to": 960, "dropoff_location_x": 187, "dropoff_location_y": 174, "payment": 549}, {"order_id": 16467, "pickup_point_id": 46467, "pickup_from": 300, "pickup_to": 900, "pickup_location_x": 121, "pickup_location_y": 136, "dropoff_point_id": 66467, "dropoff_from": 808, "dropoff_to": 1020, "dropoff_location_x": 377, "dropoff_location_y": 113, "payment": 412}, {"order_id": 16489, "pickup_point_id": 46489, "pickup_from": 390, "pickup_to": 870, "pickup_location_x": 123, "pickup_location_y": 140, "dropoff_point_id": 66489, "dropoff_from": 811, "dropoff_to": 990, "dropoff_location_x": 317, "dropoff_location_y": 173, "payment": 531}, {"order_id": 16497, "pickup_point_id": 46497, "pickup_from": 390, "pickup_to": 900, "pickup_location_x": 82, "pickup_location_y": 22, "dropoff_point_id": 66497, "dropoff_from": 812, "dropoff_to": 960, "dropoff_location_x": 183, "dropoff_location_y": 102, "payment": 290}, {"order_id": 16573, "pickup_point_id": 46573, "pickup_from": 390, "pickup_to": 900, "pickup_location_x": 100, "pickup_location_y": 82, "dropoff_point_id": 66573, "dropoff_from": 930, "dropoff_to": 960, "dropoff_location_x": 247, "dropoff_location_y": 119, "payment": 352}, {"order_id": 16579, "pickup_point_id": 46579, "pickup_from": 300, "pickup_to": 900, "pickup_location_x": 209, "pickup_location_y": 108, "dropoff_point_id": 66579, "dropoff_from": 900, "dropoff_to": 960, "dropoff_location_x": 359, "dropoff_location_y": 167, "payment": 373}, {"order_id": 16585, "pickup_point_id": 46585, "pickup_from": 330, "pickup_to": 870, "pickup_location_x": 113, "pickup_location_y": 86, "dropoff_point_id": 66585, "dropoff_from": 825, "dropoff_to": 960, "dropoff_location_x": 255, "dropoff_location_y": 250, "payment": 561}, {"order_id": 16603, "pickup_point_id": 46603, "pickup_from": 360, "pickup_to": 900, "pickup_location_x": 196, "pickup_location_y": 92, "dropoff_point_id": 66603, "dropoff_from": 900, "dropoff_to": 1020, "dropoff_location_x": 339, "dropoff_location_y": 106, "payment": 471}, {"order_id": 16606, "pickup_point_id": 46606, "pickup_from": 330, "pickup_to": 930, "pickup_location_x": 175, "pickup_location_y": 23, "dropoff_point_id": 66606, "dropoff_from": 1020, "dropoff_to": 1110, "dropoff_location_x": 275, "dropoff_location_y": 228, "payment": 547}, {"order_id": 16608, "pickup_point_id": 46608, "pickup_from": 390, "pickup_to": 887, "pickup_location_x": 41, "pickup_location_y": 114, "dropoff_point_id": 66608, "dropoff_from": 887, "dropoff_to": 947, "dropoff_location_x": 283, "dropoff_location_y": 200, "payment": 385}, {"order_id": 16669, "pickup_point_id": 46669, "pickup_from": 390, "pickup_to": 900, "pickup_location_x": 261, "pickup_location_y": 143, "dropoff_point_id": 66669, "dropoff_from": 837, "dropoff_to": 990, "dropoff_location_x": 364, "dropoff_location_y": 158, "payment": 312}, {"order_id": 16676, "pickup_point_id": 46676, "pickup_from": 390, "pickup_to": 870, "pickup_location_x": 85, "pickup_location_y": 83, "dropoff_point_id": 66676, "dropoff_from": 838, "dropoff_to": 990, "dropoff_location_x": 131, "dropoff_location_y": 280, "payment": 524}, {"order_id": 16681, "pickup_point_id": 46681, "pickup_from": 420, "pickup_to": 960, "pickup_location_x": 95, "pickup_location_y": 69, "dropoff_point_id": 66681, "dropoff_from": 839, "dropoff_to": 990, "dropoff_location_x": 99, "dropoff_location_y": 288, "payment": 550}, {"order_id": 16688, "pickup_point_id": 46688, "pickup_from": 390, "pickup_to": 900, "pickup_location_x": 159, "pickup_location_y": 60, "dropoff_point_id": 66688, "dropoff_from": 960, "dropoff_to": 990, "dropoff_location_x": 213, "dropoff_location_y": 118, "payment": 307}, {"order_id": 16701, "pickup_point_id": 46701, "pickup_from": 330, "pickup_to": 930, "pickup_location_x": 121, "pickup_location_y": 68, "dropoff_point_id": 66701, "dropoff_from": 844, "dropoff_to": 1080, "dropoff_location_x": 257, "dropoff_location_y": 230, "payment": 421}, {"order_id": 16705, "pickup_point_id": 46705, "pickup_from": 330, "pickup_to": 930, "pickup_location_x": 116, "pickup_location_y": 7, "dropoff_point_id": 66705, "dropoff_from": 960, "dropoff_to": 1050, "dropoff_location_x": 249, "dropoff_location_y": 141, "payment": 528}, {"order_id": 16714, "pickup_point_id": 46714, "pickup_from": 330, "pickup_to": 900, "pickup_location_x": 128, "pickup_location_y": 130, "dropoff_point_id": 66714, "dropoff_from": 846, "dropoff_to": 1020, "dropoff_location_x": 200, "dropoff_location_y": 154, "payment": 431}, {"order_id": 16718, "pickup_point_id": 46718, "pickup_from": 390, "pickup_to": 900, "pickup_location_x": 95, "pickup_location_y": 68, "dropoff_point_id": 66718, "dropoff_from": 900, "dropoff_to": 960, "dropoff_location_x": 170, "dropoff_location_y": 183, "payment": 377}, {"order_id": 16727, "pickup_point_id": 46727, "pickup_from": 390, "pickup_to": 930, "pickup_location_x": 159, "pickup_location_y": 63, "dropoff_point_id": 66727, "dropoff_from": 848, "dropoff_to": 1020, "dropoff_location_x": 227, "dropoff_location_y": 131, "payment": 326}, {"order_id": 16728, "pickup_point_id": 46728, "pickup_from": 360, "pickup_to": 900, "pickup_location_x": 124, "pickup_location_y": 69, "dropoff_point_id": 66728, "dropoff_from": 849, "dropoff_to": 960, "dropoff_location_x": 215, "dropoff_location_y": 120, "payment": 382}, {"order_id": 16731, "pickup_point_id": 46731, "pickup_from": 360, "pickup_to": 900, "pickup_location_x": 95, "pickup_location_y": 68, "dropoff_point_id": 66731, "dropoff_from": 900, "dropoff_to": 960, "dropoff_location_x": 170, "dropoff_location_y": 183, "payment": 377}, {"order_id": 16770, "pickup_point_id": 46770, "pickup_from": 390, "pickup_to": 900, "pickup_location_x": 58, "pickup_location_y": 130, "dropoff_point_id": 66770, "dropoff_from": 930, "dropoff_to": 990, "dropoff_location_x": 249, "dropoff_location_y": 188, "payment": 757}, {"order_id": 16781, "pickup_point_id": 46781, "pickup_from": 300, "pickup_to": 930, "pickup_location_x": 135, "pickup_location_y": 214, "dropoff_point_id": 66781, "dropoff_from": 930, "dropoff_to": 990, "dropoff_location_x": 270, "dropoff_location_y": 244, "payment": 437}, {"order_id": 16795, "pickup_point_id": 46795, "pickup_from": 330, "pickup_to": 960, "pickup_location_x": 194, "pickup_location_y": 80, "dropoff_point_id": 66795, "dropoff_from": 861, "dropoff_to": 990, "dropoff_location_x": 341, "dropoff_location_y": 90, "payment": 433}, {"order_id": 16810, "pickup_point_id": 46810, "pickup_from": 420, "pickup_to": 930, "pickup_location_x": 89, "pickup_location_y": 124, "dropoff_point_id": 66810, "dropoff_from": 863, "dropoff_to": 990, "dropoff_location_x": 335, "dropoff_location_y": 128, "payment": 418}, {"order_id": 16862, "pickup_point_id": 46862, "pickup_from": 360, "pickup_to": 930, "pickup_location_x": 199, "pickup_location_y": 49, "dropoff_point_id": 66862, "dropoff_from": 960, "dropoff_to": 1080, "dropoff_location_x": 319, "dropoff_location_y": 191, "payment": 667}, {"order_id": 16887, "pickup_point_id": 46887, "pickup_from": 300, "pickup_to": 930, "pickup_location_x": 144, "pickup_location_y": 48, "dropoff_point_id": 66887, "dropoff_from": 880, "dropoff_to": 1020, "dropoff_location_x": 200, "dropoff_location_y": 263, "payment": 482}, {"order_id": 16929, "pickup_point_id": 46929, "pickup_from": 330, "pickup_to": 930, "pickup_location_x": 55, "pickup_location_y": 123, "dropoff_point_id": 66929, "dropoff_from": 930, "dropoff_to": 1020, "dropoff_location_x": 318, "dropoff_location_y": 108, "payment": 387}, {"order_id": 16959, "pickup_point_id": 46959, "pickup_from": 360, "pickup_to": 930, "pickup_location_x": 201, "pickup_location_y": 63, "dropoff_point_id": 66959, "dropoff_from": 960, "dropoff_to": 1020, "dropoff_location_x": 244, "dropoff_location_y": 140, "payment": 409}, {"order_id": 16968, "pickup_point_id": 46968, "pickup_from": 330, "pickup_to": 960, "pickup_location_x": 31, "pickup_location_y": 125, "dropoff_point_id": 66968, "dropoff_from": 898, "dropoff_to": 990, "dropoff_location_x": 111, "dropoff_location_y": 288, "payment": 419}], "depots": [], "couriers": [{"courier_id": 36, "location_x": 201, "location_y": 4}, {"courier_id": 37, "location_x": 170, "location_y": 169}, {"courier_id": 38, "location_x": 216, "location_y": 141}, {"courier_id": 39, "location_x": 199, "location_y": 87}]}