{"orders": [{"order_id": 10716, "pickup_point_id": 40716, "pickup_from": 330, "pickup_to": 1050, "pickup_location_x": 370, "pickup_location_y": 110, "dropoff_point_id": 60716, "dropoff_from": 990, "dropoff_to": 1140, "dropoff_location_x": 14, "dropoff_location_y": 94, "payment": 540}, {"order_id": 13677, "pickup_point_id": 43677, "pickup_from": 360, "pickup_to": 1080, "pickup_location_x": 139, "pickup_location_y": 127, "dropoff_point_id": 63677, "dropoff_from": 1110, "dropoff_to": 1140, "dropoff_location_x": 52, "dropoff_location_y": 213, "payment": 360}, {"order_id": 14965, "pickup_point_id": 44965, "pickup_from": 330, "pickup_to": 1080, "pickup_location_x": 350, "pickup_location_y": 161, "dropoff_point_id": 64965, "dropoff_from": 840, "dropoff_to": 1080, "dropoff_location_x": 207, "dropoff_location_y": 167, "payment": 324}, {"order_id": 15415, "pickup_point_id": 45415, "pickup_from": 420, "pickup_to": 1020, "pickup_location_x": 312, "pickup_location_y": 48, "dropoff_point_id": 65415, "dropoff_from": 1020, "dropoff_to": 1140, "dropoff_location_x": 225, "dropoff_location_y": 82, "payment": 327}, {"order_id": 15913, "pickup_point_id": 45913, "pickup_from": 390, "pickup_to": 1020, "pickup_location_x": 358, "pickup_location_y": 109, "dropoff_point_id": 65913, "dropoff_from": 900, "dropoff_to": 1140, "dropoff_location_x": 239, "dropoff_location_y": 258, "payment": 373}, {"order_id": 15985, "pickup_point_id": 45985, "pickup_from": 360, "pickup_to": 1020, "pickup_location_x": 376, "pickup_location_y": 99, "dropoff_point_id": 65985, "dropoff_from": 1080, "dropoff_to": 1140, "dropoff_location_x": 207, "dropoff_location_y": 216, "payment": 467}, {"order_id": 16480, "pickup_point_id": 46480, "pickup_from": 390, "pickup_to": 960, "pickup_location_x": 306, "pickup_location_y": 6, "dropoff_point_id": 66480, "dropoff_from": 1110, "dropoff_to": 1170, "dropoff_location_x": 206, "dropoff_location_y": 286, "payment": 559}, {"order_id": 16664, "pickup_point_id": 46664, "pickup_from": 360, "pickup_to": 1050, "pickup_location_x": 301, "pickup_location_y": 6, "dropoff_point_id": 66664, "dropoff_from": 960, "dropoff_to": 1140, "dropoff_location_x": 116, "dropoff_location_y": 80, "payment": 695}, {"order_id": 16936, "pickup_point_id": 46936, "pickup_from": 390, "pickup_to": 1050, "pickup_location_x": 275, "pickup_location_y": 2, "dropoff_point_id": 66936, "dropoff_from": 1050, "dropoff_to": 1200, "dropoff_location_x": 122, "dropoff_location_y": 127, "payment": 413}, {"order_id": 16990, "pickup_point_id": 46990, "pickup_from": 360, "pickup_to": 1020, "pickup_location_x": 354, "pickup_location_y": 81, "dropoff_point_id": 66990, "dropoff_from": 1080, "dropoff_to": 1140, "dropoff_location_x": 215, "dropoff_location_y": 249, "payment": 459}, {"order_id": 17047, "pickup_point_id": 47047, "pickup_from": 360, "pickup_to": 1080, "pickup_location_x": 292, "pickup_location_y": 123, "dropoff_point_id": 67047, "dropoff_from": 1020, "dropoff_to": 1110, "dropoff_location_x": 119, "dropoff_location_y": 236, "payment": 511}, {"order_id": 17133, "pickup_point_id": 47133, "pickup_from": 330, "pickup_to": 1050, "pickup_location_x": 221, "pickup_location_y": 156, "dropoff_point_id": 67133, "dropoff_from": 1080, "dropoff_to": 1140, "dropoff_location_x": 155, "dropoff_location_y": 277, "payment": 413}, {"order_id": 17146, "pickup_point_id": 47146, "pickup_from": 360, "pickup_to": 1020, "pickup_location_x": 362, "pickup_location_y": 110, "dropoff_point_id": 67146, "dropoff_from": 990, "dropoff_to": 1176, "dropoff_location_x": 27, "dropoff_location_y": 66, "payment": 561}, {"order_id": 17153, "pickup_point_id": 47153, "pickup_from": 330, "pickup_to": 1080, "pickup_location_x": 360, "pickup_location_y": 74, "dropoff_point_id": 67153, "dropoff_from": 1080, "dropoff_to": 1140, "dropoff_location_x": 213, "dropoff_location_y": 292, "payment": 600}, {"order_id": 17165, "pickup_point_id": 47165, "pickup_from": 330, "pickup_to": 1050, "pickup_location_x": 307, "pickup_location_y": 88, "dropoff_point_id": 67165, "dropoff_from": 964, "dropoff_to": 1080, "dropoff_location_x": 176, "dropoff_location_y": 161, "payment": 402}, {"order_id": 17191, "pickup_point_id": 47191, "pickup_from": 360, "pickup_to": 1020, "pickup_location_x": 366, "pickup_location_y": 103, "dropoff_point_id": 67191, "dropoff_from": 985, "dropoff_to": 1110, "dropoff_location_x": 213, "dropoff_location_y": 198, "payment": 491}, {"order_id": 17195, "pickup_point_id": 47195, "pickup_from": 390, "pickup_to": 1080, "pickup_location_x": 272, "pickup_location_y": 107, "dropoff_point_id": 67195, "dropoff_from": 988, "dropoff_to": 1110, "dropoff_location_x": 51, "dropoff_location_y": 131, "payment": 493}, {"order_id": 17200, "pickup_point_id": 47200, "pickup_from": 390, "pickup_to": 1080, "pickup_location_x": 207, "pickup_location_y": 53, "dropoff_point_id": 67200, "dropoff_from": 990, "dropoff_to": 1110, "dropoff_location_x": 131, "dropoff_location_y": 141, "payment": 404}, {"order_id": 17211, "pickup_point_id": 47211, "pickup_from": 300, "pickup_to": 1080, "pickup_location_x": 202, "pickup_location_y": 4, "dropoff_point_id": 67211, "dropoff_from": 998, "dropoff_to": 1110, "dropoff_location_x": 100, "dropoff_location_y": 101, "payment": 373}, {"order_id": 17225, "pickup_point_id": 47225, "pickup_from": 420, "pickup_to": 1050, "pickup_location_x": 321, "pickup_location_y": 114, "dropoff_point_id": 67225, "dropoff_from": 1014, "dropoff_to": 1170, "dropoff_location_x": 76, "dropoff_location_y": 152, "payment": 440}, {"order_id": 17231, "pickup_point_id": 47231, "pickup_from": 300, "pickup_to": 1080, "pickup_location_x": 202, "pickup_location_y": 4, "dropoff_point_id": 67231, "dropoff_from": 1019, "dropoff_to": 1140, "dropoff_location_x": 100, "dropoff_location_y": 101, "payment": 373}, {"order_id": 17232, "pickup_point_id": 47232, "pickup_from": 360, "pickup_to": 1110, "pickup_location_x": 339, "pickup_location_y": 59, "dropoff_point_id": 67232, "dropoff_from": 1023, "dropoff_to": 1170, "dropoff_location_x": 264, "dropoff_location_y": 215, "payment": 430}, {"order_id": 17240, "pickup_point_id": 47240, "pickup_from": 300, "pickup_to": 1110, "pickup_location_x": 274, "pickup_location_y": 65, "dropoff_point_id": 67240, "dropoff_from": 1029, "dropoff_to": 1140, "dropoff_location_x": 170, "dropoff_location_y": 202, "payment": 378}, {"order_id": 17263, "pickup_point_id": 47263, "pickup_from": 330, "pickup_to": 1080, "pickup_location_x": 211, "pickup_location_y": 82, "dropoff_point_id": 67263, "dropoff_from": 1049, "dropoff_to": 1140, "dropoff_location_x": 135, "dropoff_location_y": 139, "payment": 368}, {"order_id": 17269, "pickup_point_id": 47269, "pickup_from": 390, "pickup_to": 1110, "pickup_location_x": 327, "pickup_location_y": 23, "dropoff_point_id": 67269, "dropoff_from": 1055, "dropoff_to": 1170, "dropoff_location_x": 242, "dropoff_location_y": 264, "payment": 352}], "depots": [], "couriers": [{"courier_id": 135, "location_x": 318, "location_y": 145}]}