{"orders": [{"order_id": 10003, "pickup_point_id": 40003, "pickup_from": 390, "pickup_to": 1020, "pickup_location_x": 225, "pickup_location_y": 141, "dropoff_point_id": 60003, "dropoff_from": 1050, "dropoff_to": 1080, "dropoff_location_x": 115, "dropoff_location_y": 38, "payment": 380}, {"order_id": 10240, "pickup_point_id": 40240, "pickup_from": 330, "pickup_to": 990, "pickup_location_x": 345, "pickup_location_y": 38, "dropoff_point_id": 60240, "dropoff_from": 960, "dropoff_to": 1110, "dropoff_location_x": 94, "dropoff_location_y": 13, "payment": 583}, {"order_id": 13998, "pickup_point_id": 43998, "pickup_from": 300, "pickup_to": 1020, "pickup_location_x": 344, "pickup_location_y": 65, "dropoff_point_id": 63998, "dropoff_from": 720, "dropoff_to": 1050, "dropoff_location_x": 211, "dropoff_location_y": 108, "payment": 306}, {"order_id": 14843, "pickup_point_id": 44843, "pickup_from": 330, "pickup_to": 990, "pickup_location_x": 340, "pickup_location_y": 118, "dropoff_point_id": 64843, "dropoff_from": 662, "dropoff_to": 1020, "dropoff_location_x": 96, "dropoff_location_y": 165, "payment": 409}, {"order_id": 15217, "pickup_point_id": 45217, "pickup_from": 360, "pickup_to": 960, "pickup_location_x": 371, "pickup_location_y": 92, "dropoff_point_id": 65217, "dropoff_from": 900, "dropoff_to": 1020, "dropoff_location_x": 130, "dropoff_location_y": 80, "payment": 526}, {"order_id": 15732, "pickup_point_id": 45732, "pickup_from": 390, "pickup_to": 990, "pickup_location_x": 214, "pickup_location_y": 107, "dropoff_point_id": 65732, "dropoff_from": 733, "dropoff_to": 1050, "dropoff_location_x": 20, "dropoff_location_y": 71, "payment": 522}, {"order_id": 15869, "pickup_point_id": 45869, "pickup_from": 330, "pickup_to": 1050, "pickup_location_x": 229, "pickup_location_y": 125, "dropoff_point_id": 65869, "dropoff_from": 990, "dropoff_to": 1080, "dropoff_location_x": 105, "dropoff_location_y": 111, "payment": 368}, {"order_id": 16079, "pickup_point_id": 46079, "pickup_from": 300, "pickup_to": 1020, "pickup_location_x": 309, "pickup_location_y": 140, "dropoff_point_id": 66079, "dropoff_from": 990, "dropoff_to": 1080, "dropoff_location_x": 202, "dropoff_location_y": 73, "payment": 462}, {"order_id": 16087, "pickup_point_id": 46087, "pickup_from": 390, "pickup_to": 1020, "pickup_location_x": 257, "pickup_location_y": 236, "dropoff_point_id": 66087, "dropoff_from": 1080, "dropoff_to": 1110, "dropoff_location_x": 57, "dropoff_location_y": 187, "payment": 506}, {"order_id": 16547, "pickup_point_id": 46547, "pickup_from": 360, "pickup_to": 990, "pickup_location_x": 365, "pickup_location_y": 110, "dropoff_point_id": 66547, "dropoff_from": 819, "dropoff_to": 1020, "dropoff_location_x": 224, "dropoff_location_y": 140, "payment": 439}, {"order_id": 16684, "pickup_point_id": 46684, "pickup_from": 300, "pickup_to": 1020, "pickup_location_x": 229, "pickup_location_y": 113, "dropoff_point_id": 66684, "dropoff_from": 840, "dropoff_to": 1080, "dropoff_location_x": 95, "dropoff_location_y": 80, "payment": 385}, {"order_id": 16725, "pickup_point_id": 46725, "pickup_from": 330, "pickup_to": 960, "pickup_location_x": 240, "pickup_location_y": 168, "dropoff_point_id": 66725, "dropoff_from": 848, "dropoff_to": 1110, "dropoff_location_x": 73, "dropoff_location_y": 186, "payment": 404}, {"order_id": 16736, "pickup_point_id": 46736, "pickup_from": 300, "pickup_to": 960, "pickup_location_x": 321, "pickup_location_y": 153, "dropoff_point_id": 66736, "dropoff_from": 850, "dropoff_to": 990, "dropoff_location_x": 28, "dropoff_location_y": 117, "payment": 494}, {"order_id": 16764, "pickup_point_id": 46764, "pickup_from": 300, "pickup_to": 960, "pickup_location_x": 243, "pickup_location_y": 159, "dropoff_point_id": 66764, "dropoff_from": 855, "dropoff_to": 1080, "dropoff_location_x": 46, "dropoff_location_y": 71, "payment": 416}, {"order_id": 16802, "pickup_point_id": 46802, "pickup_from": 300, "pickup_to": 1020, "pickup_location_x": 189, "pickup_location_y": 125, "dropoff_point_id": 66802, "dropoff_from": 960, "dropoff_to": 1080, "dropoff_location_x": 67, "dropoff_location_y": 186, "payment": 348}, {"order_id": 16844, "pickup_point_id": 46844, "pickup_from": 390, "pickup_to": 960, "pickup_location_x": 313, "pickup_location_y": 54, "dropoff_point_id": 66844, "dropoff_from": 1020, "dropoff_to": 1050, "dropoff_location_x": 134, "dropoff_location_y": 92, "payment": 408}, {"order_id": 16858, "pickup_point_id": 46858, "pickup_from": 420, "pickup_to": 960, "pickup_location_x": 375, "pickup_location_y": 83, "dropoff_point_id": 66858, "dropoff_from": 875, "dropoff_to": 1020, "dropoff_location_x": 34, "dropoff_location_y": 163, "payment": 579}, {"order_id": 16919, "pickup_point_id": 46919, "pickup_from": 330, "pickup_to": 990, "pickup_location_x": 247, "pickup_location_y": 167, "dropoff_point_id": 66919, "dropoff_from": 990, "dropoff_to": 1050, "dropoff_location_x": 127, "dropoff_location_y": 139, "payment": 460}, {"order_id": 16931, "pickup_point_id": 46931, "pickup_from": 390, "pickup_to": 960, "pickup_location_x": 354, "pickup_location_y": 92, "dropoff_point_id": 66931, "dropoff_from": 990, "dropoff_to": 1020, "dropoff_location_x": 168, "dropoff_location_y": 60, "payment": 443}, {"order_id": 16948, "pickup_point_id": 46948, "pickup_from": 360, "pickup_to": 960, "pickup_location_x": 239, "pickup_location_y": 112, "dropoff_point_id": 66948, "dropoff_from": 894, "dropoff_to": 1020, "dropoff_location_x": 23, "dropoff_location_y": 115, "payment": 396}, {"order_id": 16975, "pickup_point_id": 46975, "pickup_from": 330, "pickup_to": 960, "pickup_location_x": 201, "pickup_location_y": 150, "dropoff_point_id": 66975, "dropoff_from": 1020, "dropoff_to": 1050, "dropoff_location_x": 2, "dropoff_location_y": 93, "payment": 442}, {"order_id": 16989, "pickup_point_id": 46989, "pickup_from": 360, "pickup_to": 1050, "pickup_location_x": 254, "pickup_location_y": 168, "dropoff_point_id": 66989, "dropoff_from": 906, "dropoff_to": 1080, "dropoff_location_x": 32, "dropoff_location_y": 154, "payment": 509}, {"order_id": 16998, "pickup_point_id": 46998, "pickup_from": 420, "pickup_to": 960, "pickup_location_x": 298, "pickup_location_y": 50, "dropoff_point_id": 66998, "dropoff_from": 909, "dropoff_to": 1020, "dropoff_location_x": 81, "dropoff_location_y": 20, "payment": 528}, {"order_id": 17005, "pickup_point_id": 47005, "pickup_from": 330, "pickup_to": 990, "pickup_location_x": 226, "pickup_location_y": 129, "dropoff_point_id": 67005, "dropoff_from": 910, "dropoff_to": 1050, "dropoff_location_x": 41, "dropoff_location_y": 130, "payment": 609}, {"order_id": 17006, "pickup_point_id": 47006, "pickup_from": 420, "pickup_to": 990, "pickup_location_x": 269, "pickup_location_y": 98, "dropoff_point_id": 67006, "dropoff_from": 911, "dropoff_to": 1080, "dropoff_location_x": 69, "dropoff_location_y": 9, "payment": 433}, {"order_id": 17011, "pickup_point_id": 47011, "pickup_from": 360, "pickup_to": 990, "pickup_location_x": 266, "pickup_location_y": 180, "dropoff_point_id": 67011, "dropoff_from": 913, "dropoff_to": 1080, "dropoff_location_x": 92, "dropoff_location_y": 224, "payment": 480}, {"order_id": 17019, "pickup_point_id": 47019, "pickup_from": 420, "pickup_to": 990, "pickup_location_x": 347, "pickup_location_y": 47, "dropoff_point_id": 67019, "dropoff_from": 1020, "dropoff_to": 1110, "dropoff_location_x": 111, "dropoff_location_y": 46, "payment": 476}, {"order_id": 17031, "pickup_point_id": 47031, "pickup_from": 420, "pickup_to": 990, "pickup_location_x": 266, "pickup_location_y": 45, "dropoff_point_id": 67031, "dropoff_from": 1020, "dropoff_to": 1050, "dropoff_location_x": 131, "dropoff_location_y": 36, "payment": 458}, {"order_id": 17050, "pickup_point_id": 47050, "pickup_from": 300, "pickup_to": 990, "pickup_location_x": 371, "pickup_location_y": 92, "dropoff_point_id": 67050, "dropoff_from": 922, "dropoff_to": 1050, "dropoff_location_x": 130, "dropoff_location_y": 80, "payment": 626}, {"order_id": 17051, "pickup_point_id": 47051, "pickup_from": 390, "pickup_to": 990, "pickup_location_x": 317, "pickup_location_y": 88, "dropoff_point_id": 67051, "dropoff_from": 1020, "dropoff_to": 1080, "dropoff_location_x": 204, "dropoff_location_y": 96, "payment": 321}, {"order_id": 17095, "pickup_point_id": 47095, "pickup_from": 390, "pickup_to": 1020, "pickup_location_x": 297, "pickup_location_y": 22, "dropoff_point_id": 67095, "dropoff_from": 934, "dropoff_to": 1080, "dropoff_location_x": 159, "dropoff_location_y": 51, "payment": 397}, {"order_id": 17096, "pickup_point_id": 47096, "pickup_from": 390, "pickup_to": 1020, "pickup_location_x": 278, "pickup_location_y": 114, "dropoff_point_id": 67096, "dropoff_from": 1050, "dropoff_to": 1110, "dropoff_location_x": 117, "dropoff_location_y": 57, "payment": 475}, {"order_id": 17126, "pickup_point_id": 47126, "pickup_from": 420, "pickup_to": 1020, "pickup_location_x": 278, "pickup_location_y": 114, "dropoff_point_id": 67126, "dropoff_from": 943, "dropoff_to": 1080, "dropoff_location_x": 118, "dropoff_location_y": 68, "payment": 475}, {"order_id": 17160, "pickup_point_id": 47160, "pickup_from": 390, "pickup_to": 1020, "pickup_location_x": 225, "pickup_location_y": 141, "dropoff_point_id": 67160, "dropoff_from": 1050, "dropoff_to": 1080, "dropoff_location_x": 126, "dropoff_location_y": 51, "payment": 380}, {"order_id": 17162, "pickup_point_id": 47162, "pickup_from": 420, "pickup_to": 1020, "pickup_location_x": 190, "pickup_location_y": 161, "dropoff_point_id": 67162, "dropoff_from": 1020, "dropoff_to": 1080, "dropoff_location_x": 51, "dropoff_location_y": 85, "payment": 404}, {"order_id": 17173, "pickup_point_id": 47173, "pickup_from": 300, "pickup_to": 1050, "pickup_location_x": 266, "pickup_location_y": 45, "dropoff_point_id": 67173, "dropoff_from": 974, "dropoff_to": 1080, "dropoff_location_x": 131, "dropoff_location_y": 36, "payment": 458}], "depots": [], "couriers": [{"courier_id": 223, "location_x": 201, "location_y": 155}, {"courier_id": 224, "location_x": 144, "location_y": 131}]}